plane/__init__.py
plane/config.py
plane/api/__init__.py
plane/api/base_resource.py
plane/api/cycles.py
plane/api/epics.py
plane/api/intake.py
plane/api/labels.py
plane/api/modules.py
plane/api/pages.py
plane/api/projects.py
plane/api/states.py
plane/api/stickies.py
plane/api/users.py
plane/api/work_item_types.py
plane/api/workspaces.py
plane/api/agent_runs/__init__.py
plane/api/agent_runs/activities.py
plane/api/agent_runs/base.py
plane/api/customers/__init__.py
plane/api/customers/base.py
plane/api/customers/properties.py
plane/api/customers/requests.py
plane/api/initiatives/__init__.py
plane/api/initiatives/base.py
plane/api/initiatives/epics.py
plane/api/initiatives/labels.py
plane/api/initiatives/projects.py
plane/api/teamspaces/__init__.py
plane/api/teamspaces/base.py
plane/api/teamspaces/members.py
plane/api/teamspaces/projects.py
plane/api/work_item_properties/__init__.py
plane/api/work_item_properties/base.py
plane/api/work_item_properties/options.py
plane/api/work_item_properties/values.py
plane/api/work_items/__init__.py
plane/api/work_items/activities.py
plane/api/work_items/attachments.py
plane/api/work_items/base.py
plane/api/work_items/comments.py
plane/api/work_items/links.py
plane/api/work_items/relations.py
plane/api/work_items/work_logs.py
plane/client/__init__.py
plane/client/oauth_client.py
plane/client/plane_client.py
plane/errors/__init__.py
plane/errors/errors.py
plane/models/__init__.py
plane/models/agent_runs.py
plane/models/customers.py
plane/models/cycles.py
plane/models/enums.py
plane/models/epics.py
plane/models/initiatives.py
plane/models/intake.py
plane/models/labels.py
plane/models/modules.py
plane/models/pages.py
plane/models/pagination.py
plane/models/projects.py
plane/models/query_params.py
plane/models/states.py
plane/models/stickies.py
plane/models/teamspaces.py
plane/models/users.py
plane/models/work_item_properties.py
plane/models/work_item_property_configurations.py
plane/models/work_item_types.py
plane/models/work_items.py
plane_sdk-0.2.4.dist-info/LICENSE
plane_sdk-0.2.4.dist-info/METADATA
plane_sdk-0.2.4.dist-info/WHEEL
plane_sdk-0.2.4.dist-info/top_level.txt
plane_sdk-0.2.4.dist-info/RECORD
