Metadata-Version: 2.1
Name: plane-sdk
Version: 0.2.4
Summary: Python SDK for Plane API
Author-email: Plane <engineering@plane.so>
License: MIT
Requires-Python: >=3.10
License-File: LICENSE
Requires-Dist: requests>=2.31.0
Requires-Dist: pydantic>=2.4.0
